polars_fastembed-0.1.17.dist-info/METADATA
polars_fastembed-0.1.17.dist-info/WHEEL
polars_fastembed/__init__.py
polars_fastembed/_ort_loader.py
polars_fastembed/_polars_fastembed.abi3.so
polars_fastembed/utils.py
polars_fastembed-0.1.17.dist-info/RECORD
