Metadata-Version: 2.4
Name: polars_fastembed
Version: 0.1.17
Classifier: Development Status :: 4 - Beta
Classifier: Intended Audience :: Developers
Classifier: Natural Language :: English
Classifier: License :: OSI Approved :: MIT License
Classifier: Operating System :: MacOS
Classifier: Operating System :: Microsoft :: Windows
Classifier: Operating System :: OS Independent
Classifier: Operating System :: POSIX :: Linux
Classifier: Programming Language :: Rust
Classifier: Programming Language :: Python
Classifier: Programming Language :: Python :: Implementation :: CPython
Classifier: Programming Language :: Python :: 3
Classifier: Programming Language :: Python :: 3.10
Classifier: Programming Language :: Python :: 3.10
Classifier: Programming Language :: Python :: 3.11
Classifier: Programming Language :: Python :: 3.12
Classifier: Programming Language :: Python :: 3.13
Requires-Dist: polars>=1.36.0
Requires-Dist: polars-distance>=0.5.3
Requires-Dist: polars-fastembed-cpu>=0.1.14 ; extra == 'cpu'
Requires-Dist: polars-fastembed-cuda>=0.1.14 ; extra == 'cuda'
Requires-Dist: polars[rtcompat] ; extra == 'polars-lts-cpu'
Provides-Extra: cpu
Provides-Extra: cuda
Provides-Extra: polars-lts-cpu
Summary: A Polars plugin for text embeddings in DataFrames
Author-email: Louis Maddox <louismmx@gmail.com>
Requires-Python: >=3.10
